chaanbot/__init__.py
chaanbot/client.py
chaanbot/command_utility.py
chaanbot/database.py
chaanbot/matrix.py
chaanbot/module_loader.py
chaanbot/module_runner.py
chaanbot/start.py
chaanbot/modules/__init__.py
chaanbot/modules/alive.py
chaanbot/modules/chan_save.py
chaanbot/modules/darksky_weather.py
chaanbot/modules/highlight.py
chaanbot/modules/revamp.py
chaanbot/modules/rewrite_youtube_shorts.py
chaanbot/modules/twitter.py
chaanbot/modules/weather.py
tests/__init__.py
tests/test_alive.py
tests/test_chan_save.py
tests/test_client.py
tests/test_command_utility.py
tests/test_darksky_weather.py
tests/test_database.py
tests/test_highlight.py
tests/test_matrix.py
tests/test_module_loader.py
tests/test_module_runner.py
tests/test_revAMP.py
tests/test_rewrite_youtube_shorts.py
tests/test_start.py
tests/test_twitter.py
tests/test_weather.py
chaanbot-3.1.1.dist-info/LICENSE
chaanbot-3.1.1.dist-info/METADATA
chaanbot-3.1.1.dist-info/WHEEL
chaanbot-3.1.1.dist-info/entry_points.txt
chaanbot-3.1.1.dist-info/top_level.txt
chaanbot-3.1.1.dist-info/RECORD
