Metadata-Version: 2.1
Name: chaanbot
Version: 3.1.1
Summary: A Matrix chat bot
Home-page: https://github.com/RichardNysater/chaanbot
Author: Richard Nysäter
Author-email: richard@nysater.org
License: GPLv3+
Keywords: m,a,t,r,i,x, ,c,h,a,t, ,b,o,t
Platform: UNKNOWN
Classifier: Development Status :: 4 - Beta
Classifier: Topic :: Communications :: Chat
Classifier: Programming Language :: Python :: 3.5
Classifier: Programming Language :: Python :: 3.6
Classifier: Programming Language :: Python :: 3.7
Classifier: Programming Language :: Python :: 3.8
Classifier: Programming Language :: Python :: 3.9
Classifier: License :: OSI Approved :: GNU General Public License v3 or later (GPLv3+)
Classifier: Operating System :: OS Independent
Requires-Python: >=3.5
License-File: LICENSE
Requires-Dist: matrix-nio
Requires-Dist: appdirs
Requires-Dist: requests
Requires-Dist: beautifulsoup4
